MANIFEST.in
setup.py
Toxygen.egg-info/PKG-INFO
Toxygen.egg-info/SOURCES.txt
Toxygen.egg-info/dependency_links.txt
Toxygen.egg-info/entry_points.txt
Toxygen.egg-info/top_level.txt
toxygen/__init__.py
toxygen/avwidgets.py
toxygen/basecontact.py
toxygen/bootstrap.py
toxygen/callbacks.py
toxygen/calls.py
toxygen/contact.py
toxygen/file_transfers.py
toxygen/friend.py
toxygen/group_chat.py
toxygen/history.py
toxygen/items_factory.py
toxygen/libtox.py
toxygen/list_items.py
toxygen/loginscreen.py
toxygen/main.py
toxygen/mainscreen.py
toxygen/mainscreen_widgets.py
toxygen/menu.py
toxygen/messages.py
toxygen/notifications.py
toxygen/passwordscreen.py
toxygen/plugin_support.py
toxygen/profile.py
toxygen/screen_sharing.py
toxygen/settings.py
toxygen/smileys.py
toxygen/tox.py
toxygen/tox_dns.py
toxygen/toxav.py
toxygen/toxav_enums.py
toxygen/toxcore_enums_and_consts.py
toxygen/toxencryptsave.py
toxygen/toxencryptsave_enums_and_consts.py
toxygen/toxes.py
toxygen/toxygen_updater.py
toxygen/updater.py
toxygen/util.py
toxygen/widgets.py
toxygen/images/accept.png
toxygen/images/accept_audio.png
toxygen/images/accept_video.png
toxygen/images/avatar.png
toxygen/images/busy.png
toxygen/images/busy_notification.png
toxygen/images/call.png
toxygen/images/call_video.png
toxygen/images/decline.png
toxygen/images/decline_call.png
toxygen/images/file.png
toxygen/images/finish_call.png
toxygen/images/finish_call_video.png
toxygen/images/group.png
toxygen/images/icon.ico
toxygen/images/icon.png
toxygen/images/icon_new_messages.png
toxygen/images/idle.png
toxygen/images/idle_notification.png
toxygen/images/incoming_call.png
toxygen/images/incoming_call_video.png
toxygen/images/menu.png
toxygen/images/offline.png
toxygen/images/offline_notification.png
toxygen/images/online.png
toxygen/images/online_notification.png
toxygen/images/pause.png
toxygen/images/resume.png
toxygen/images/screenshot.png
toxygen/images/search.png
toxygen/images/send.png
toxygen/images/smiley.png
toxygen/images/spinner.gif
toxygen/images/sticker.png
toxygen/images/typing.png
toxygen/libs/libsodium.a
toxygen/libs/libtox.dll
toxygen/plugins/__init__.py
toxygen/plugins/ae.py
