Metadata-Version: 1.1
Name: Toxygen
Version: 0.4.0.0
Summary: Toxygen - Tox client
Home-page: https://github.com/toxygen-project/toxygen/
Author: Ingvar
Author-email: UNKNOWN
License: GPL3
Keywords: toxygen tox messenger
Platform: UNKNOWN
Classifier: Programming Language :: Python :: 3 :: Only
Classifier: Programming Language :: Python :: 3.5
Classifier: Programming Language :: Python :: 3.6
